{"last_updated": "2021-01-25 19:40:31 GMT", "keyboards": {"4by3": {"keyboard_name": "4by3", "keyboard_folder": "4by3", "keymaps": {}, "layouts": {"LAYOUT_horizontal": {"key_count": 12, "layout": [{"x": 0, "y": 0}, {"x": 1, "y": 0}, {"x": 2, "y": 0}, {"x": 3, "y": 0}, {"x": 0, "y": 1}, {"x": 1, "y": 1}, {"x": 2, "y": 1}, {"x": 3, "y": 1}, {"x": 0, "y": 2}, {"x": 1, "y": 2}, {"x": 2, "y": 2}, {"x": 3, "y": 2}], "filename": "keyboards/4by3/4by3.h", "c_macro": false}, "LAYOUT_vertical_right": {"key_count": 12, "layout": [{"x": 0, "y": 0}, {"x": 1, "y": 0}, {"x": 2, "y": 0}, {"x": 0, "y": 1}, {"x": 1, "y": 1}, {"x": 2, "y": 1}, {"x": 0, "y": 2}, {"x": 1, "y": 2}, {"x": 2, "y": 2}, {"x": 0, "y": 3}, {"x": 1, "y": 3}, {"x": 2, "y": 3}], "filename": "keyboards/4by3/4by3.h", "c_macro": false}, "LAYOUT_vertical_left": {"key_count": 12, "layout": [{"x": 0, "y": 0}, {"x": 1, "y": 0}, {"x": 2, "y": 0}, {"x": 0, "y": 1}, {"x": 1, "y": 1}, {"x": 2, "y": 1}, {"x": 0, "y": 2}, {"x": 1, "y": 2}, {"x": 2, "y": 2}, {"x": 0, "y": 3}, {"x": 1, "y": 3}, {"x": 2, "y": 3}], "filename": "keyboards/4by3/4by3.h", "c_macro": false}, "LAYOUT": {"key_count": 12, "layout": [{"x": 0, "y": 0}, {"x": 1, "y": 0}, {"x": 2, "y": 0}, {"x": 3, "y": 0}, {"x": 0, "y": 1}, {"x": 1, "y": 1}, {"x": 2, "y": 1}, {"x": 3, "y": 1}, {"x": 0, "y": 2}, {"x": 1, "y": 2}, {"x": 2, "y": 2}, {"x": 3, "y": 2}], "filename": "keyboards/4by3/4by3.h", "c_macro": false}}, "parse_errors": [], "parse_warnings": [], "maintainer": "eliassjogreen", "url": "https://github.com/eliassjogreen/4by3", "width": 4, "height": 3, "debounce": 5, "diode_direction": "COL2ROW", "indicators": {}, "matrix_size": {"cols": 4, "rows": 3}, "matrix_pins": {"cols": ["C6", "D7", "E6", "B4"], "rows": ["D1", "D0", "D4"]}, "usb": {"vid": "0xEEEE", "pid": "0x2019", "device_ver": "0x0001"}, "rgblight": {"sleep": false, "split": false}, "processor_type": "avr", "bootloader": "caterina", "platform": "unknown", "protocol": "LUFA", "processor": "atmega32u4", "community_layouts": [], "config_h_features": {"extrakey": true, "nkro": true, "console": true, "command": true}, "features": {"extrakey": true, "nkro": true, "console": true, "command": true}}}}