{"last_updated": "2021-01-21 06:02:00 GMT", "keyboards": {"1upkeyboards/sweet16/v2/proton_c": {"keyboard_name": "Sweet 16", "keyboard_folder": "1upkeyboards/sweet16/v2/proton_c", "keymaps": {}, "layouts": {"LAYOUT_ortho_4x4": {"key_count": 16, "layout": [{"x": 0, "y": 0}, {"x": 1, "y": 0}, {"x": 2, "y": 0}, {"x": 3, "y": 0}, {"x": 0, "y": 1}, {"x": 1, "y": 1}, {"x": 2, "y": 1}, {"x": 3, "y": 1}, {"x": 0, "y": 2}, {"x": 1, "y": 2}, {"x": 2, "y": 2}, {"x": 3, "y": 2}, {"x": 0, "y": 3}, {"x": 1, "y": 3}, {"x": 2, "y": 3}, {"x": 3, "y": 3}], "filename": "keyboards/1upkeyboards/sweet16/v2/proton_c/proton_c.h", "c_macro": false}, "LAYOUT_numpad_4x4": {"key_count": 13, "layout": [{"x": 0, "y": 0}, {"x": 1, "y": 0}, {"x": 2, "y": 0}, {"x": 3, "y": 0, "h": 2}, {"x": 0, "y": 1}, {"x": 1, "y": 1}, {"x": 2, "y": 1}, {"x": 0, "y": 2}, {"x": 1, "y": 2}, {"x": 2, "y": 2}, {"x": 3, "y": 2, "h": 2}, {"x": 0, "y": 3, "w": 2}, {"x": 2, "y": 3}], "filename": "keyboards/1upkeyboards/sweet16/v2/proton_c/proton_c.h", "c_macro": false}}, "parse_errors": [], "parse_warnings": [], "maintainer": "skullydazed", "url": "", "width": 4, "height": 4, "debounce": 5, "diode_direction": "COL2ROW", "indicators": {}, "matrix_size": {"cols": 4, "rows": 4}, "matrix_pins": {"cols": ["D1", "D0", "D4", "C6"], "rows": ["F4", "F5", "F6", "F7"]}, "usb": {"vid": "0x6F75", "pid": "0x0161", "device_ver": "0x0001"}, "rgblight": {"led_count": 1, "pin": "B1", "hue_steps": 8, "saturation_steps": 8, "brightness_steps": 8, "sleep": false, "split": false, "animations": {"all": true}}, "processor_type": "arm", "protocol": "ChibiOS", "processor": "STM32F303", "bootloader": "stm32-dfu", "platform": "STM32", "board": "QMK_PROTON_C", "community_layouts": [], "config_h_features": {"console": true, "encoder": true, "audio": true, "mousekey": true, "extrakey": true, "command": false, "sleep_led": false, "nkro": true, "rgblight": false}, "features": {"console": true, "encoder": true, "audio": true, "mousekey": true, "extrakey": true, "command": false, "sleep_led": false, "nkro": true, "rgblight": false}}}}