{"last_updated": "2021-02-16 00:30:10 GMT", "keyboards": {"evyd13/mx5160": {"keyboard_name": "mx5160", "keyboard_folder": "evyd13/mx5160", "keymaps": {}, "layouts": {"LAYOUT_all": {"key_count": 91, "layout": [{"x": 0, "y": 0}, {"x": 1, "y": 0}, {"x": 2.5, "y": 0}, {"x": 3.5, "y": 0}, {"x": 4.5, "y": 0}, {"x": 5.5, "y": 0}, {"x": 6.5, "y": 0}, {"x": 7.5, "y": 0}, {"x": 8.5, "y": 0}, {"x": 9.5, "y": 0}, {"x": 10.5, "y": 0}, {"x": 11.5, "y": 0}, {"x": 12.5, "y": 0}, {"x": 13.5, "y": 0}, {"x": 14.5, "y": 0}, {"x": 15.5, "y": 0}, {"x": 16.5, "y": 0}, {"x": 18, "y": 0}, {"x": 19, "y": 0}, {"x": 20, "y": 0}, {"x": 21, "y": 0}, {"x": 0, "y": 1}, {"x": 1, "y": 1}, {"x": 2.5, "y": 1, "w": 1.5}, {"x": 4, "y": 1}, {"x": 5, "y": 1}, {"x": 6, "y": 1}, {"x": 7, "y": 1}, {"x": 8, "y": 1}, {"x": 9, "y": 1}, {"x": 10, "y": 1}, {"x": 11, "y": 1}, {"x": 12, "y": 1}, {"x": 13, "y": 1}, {"x": 14, "y": 1}, {"x": 15, "y": 1}, {"x": 16, "y": 1, "w": 1.5}, {"x": 18, "y": 1}, {"x": 19, "y": 1}, {"x": 20, "y": 1}, {"x": 21, "y": 1}, {"x": 0, "y": 2}, {"x": 1, "y": 2}, {"x": 2.5, "y": 2, "w": 1.75}, {"x": 4.25, "y": 2}, {"x": 5.25, "y": 2}, {"x": 6.25, "y": 2}, {"x": 7.25, "y": 2}, {"x": 8.25, "y": 2}, {"x": 9.25, "y": 2}, {"x": 10.25, "y": 2}, {"x": 11.25, "y": 2}, {"x": 12.25, "y": 2}, {"x": 13.25, "y": 2}, {"x": 14.25, "y": 2}, {"x": 15.25, "y": 2}, {"x": 16.25, "y": 2, "w": 1.25}, {"x": 18, "y": 2}, {"x": 19, "y": 2}, {"x": 20, "y": 2}, {"x": 21, "y": 2}, {"x": 0, "y": 3}, {"x": 1, "y": 3}, {"x": 2.5, "y": 3, "w": 1.25}, {"x": 3.75, "y": 3}, {"x": 4.75, "y": 3}, {"x": 5.75, "y": 3}, {"x": 6.75, "y": 3}, {"x": 7.75, "y": 3}, {"x": 8.75, "y": 3}, {"x": 9.75, "y": 3}, {"x": 10.75, "y": 3}, {"x": 11.75, "y": 3}, {"x": 12.75, "y": 3}, {"x": 13.75, "y": 3}, {"x": 14.75, "y": 3, "w": 1.75}, {"x": 16.5, "y": 3}, {"x": 18, "y": 3}, {"x": 19, "y": 3}, {"x": 20, "y": 3}, {"x": 0, "y": 4}, {"x": 1, "y": 4}, {"x": 2.5, "y": 4, "w": 1.5}, {"x": 5, "y": 4, "w": 1.5}, {"x": 6.5, "y": 4, "w": 7}, {"x": 13.5, "y": 4, "w": 1.5}, {"x": 16, "y": 4, "w": 1.5}, {"x": 18, "y": 4}, {"x": 19, "y": 4}, {"x": 20, "y": 4}, {"x": 21, "y": 3, "h": 2}], "filename": "keyboards/evyd13/mx5160/mx5160.h", "c_macro": false}}, "parse_errors": [], "parse_warnings": [], "maintainer": "qmk", "url": "https://github.com/evyd13/mx-5160", "width": 22, "height": 5, "debounce": 5, "usb": {"device_ver": "0x0001", "pid": "0x5160", "vid": "0x4705"}, "diode_direction": "ROW2COL", "manufacturer": "Evyd13", "matrix_size": {"cols": 10, "rows": 10}, "matrix_pins": {"cols": ["D0", "D1", "D2", "F7", "F6", "F5", "F4", "F1", "F0", "E6"], "rows": ["C6", "C7", "B5", "B6", "D7", "B4", "D4", "D6", "D5", "D3"]}, "processor": "atmega32u4", "processor_type": "avr", "platform": "unknown", "protocol": "LUFA", "bootloader": "qmk-dfu", "config_h_features": {"bootmagic": false, "mousekey": false, "extrakey": true, "console": false, "command": false, "sleep_led": false, "nkro": false, "backlight": false, "rgblight": false, "midi": false, "unicode": false, "bluetooth": false, "audio": false}, "features": {"bootmagic": false, "mousekey": false, "extrakey": true, "console": false, "command": false, "sleep_led": false, "nkro": false, "backlight": false, "rgblight": false, "midi": false, "unicode": false, "bluetooth": false, "audio": false}}}}