{"last_updated": "2021-02-07 20:58:45 GMT", "keyboards": {"lazydesigners/the30": {"keyboard_name": "THE30", "keyboard_folder": "lazydesigners/the30", "keymaps": {}, "layouts": {"LAYOUT_ortho_3x10": {"key_count": 30, "layout": [{"label": "Q", "x": 0, "y": 0}, {"label": "W", "x": 1, "y": 0}, {"label": "E", "x": 2, "y": 0}, {"label": "R", "x": 3, "y": 0}, {"label": "T", "x": 4, "y": 0}, {"label": "Y", "x": 5, "y": 0}, {"label": "U", "x": 6, "y": 0}, {"label": "I", "x": 7, "y": 0}, {"label": "O", "x": 8, "y": 0}, {"label": "P", "x": 9, "y": 0}, {"label": "A", "x": 0, "y": 1}, {"label": "S", "x": 1, "y": 1}, {"label": "D", "x": 2, "y": 1}, {"label": "F", "x": 3, "y": 1}, {"label": "G", "x": 4, "y": 1}, {"label": "H", "x": 5, "y": 1}, {"label": "J", "x": 6, "y": 1}, {"label": "K", "x": 7, "y": 1}, {"label": "L", "x": 8, "y": 1}, {"label": "ENTER", "x": 9, "y": 1}, {"label": "Z", "x": 0, "y": 2}, {"label": "X", "x": 1, "y": 2}, {"label": "C", "x": 2, "y": 2}, {"label": "V", "x": 3, "y": 2}, {"label": "B", "x": 4, "y": 2}, {"label": "N", "x": 5, "y": 2}, {"label": "M", "x": 6, "y": 2}, {"label": ",", "x": 7, "y": 2}, {"label": ".", "x": 8, "y": 2}, {"label": "/", "x": 9, "y": 2}], "filename": "keyboards/lazydesigners/the30/the30.h", "c_macro": false}}, "parse_errors": [], "parse_warnings": [], "maintainer": "Erovia", "url": "http://lazydesigners.cn", "width": 10, "height": 3, "usb": {"device_ver": "0x0001", "pid": "0x0030", "vid": "0x4C44"}, "diode_direction": "COL2ROW", "manufacturer": "LazyDesigners", "matrix_size": {"cols": 10, "rows": 3}, "matrix_pins": {"cols": ["B1", "B2", "B3", "D4", "D6", "D7", "B4", "B5", "B6", "C6"], "rows": ["D0", "D1", "D2"]}, "processor": "atmega32u4", "processor_type": "avr", "platform": "unknown", "protocol": "LUFA", "bootloader": "atmel-dfu", "community_layouts": ["ortho_3x10"], "config_h_features": {"mousekey": true, "extrakey": true, "console": false, "command": false, "sleep_led": false, "nkro": true, "backlight": true, "rgblight": false, "midi": false, "bluetooth": false, "audio": false, "fauxclicky": false, "bootmagic_lite": true}, "features": {"mousekey": true, "extrakey": true, "console": false, "command": false, "sleep_led": false, "nkro": true, "backlight": true, "rgblight": false, "midi": false, "bluetooth": false, "audio": false, "fauxclicky": false, "bootmagic_lite": true}}}}