{"last_updated": "2021-01-19 13:21:06 GMT", "keyboards": {"handwired/obuwunkunubi/spaget": {"keyboard_name": "spaget", "keyboard_folder": "handwired/obuwunkunubi/spaget", "keymaps": {}, "layouts": {"LAYOUT": {"key_count": 23, "layout": [{"x": 0, "y": 0}, {"x": 3, "y": 0}, {"x": 0, "y": 1.5}, {"x": 1, "y": 1.5}, {"x": 2, "y": 1.5}, {"x": 3, "y": 1.5}, {"x": 0, "y": 2.5}, {"x": 1, "y": 2.5}, {"x": 2, "y": 2.5}, {"x": 3, "y": 2.5}, {"x": 0, "y": 3.5}, {"x": 1, "y": 3.5}, {"x": 2, "y": 3.5}, {"x": 0, "y": 4.5}, {"x": 1, "y": 4.5}, {"x": 2, "y": 4.5}, {"x": 3, "y": 3.5, "h": 2}, {"x": 0, "y": 5.5}, {"x": 1, "y": 5.5}, {"x": 2, "y": 5.5}, {"x": 0, "y": 6.5, "w": 2}, {"x": 2, "y": 6.5}, {"x": 3, "y": 5.5, "h": 2}], "filename": "keyboards/handwired/obuwunkunubi/spaget/spaget.h", "c_macro": false}}, "parse_errors": [], "parse_warnings": [], "maintainer": "obuwunkunubi", "url": "", "width": 4, "height": 7.5, "diode_direction": "COL2ROW", "indicators": {}, "matrix_size": {"cols": 4, "rows": 6}, "matrix_pins": {"cols": ["B1", "B3", "B2", "B6"], "rows": ["D4", "C6", "D7", "E6", "B4", "B5"]}, "usb": {"vid": "0x1337", "pid": "0x6969", "device_ver": "0x0001"}, "rgblight": {"sleep": false, "split": false}, "processor_type": "avr", "bootloader": "caterina", "platform": "unknown", "protocol": "LUFA", "processor": "atmega32u4", "community_layouts": [], "config_h_features": {"mousekey": true, "extrakey": true, "console": false, "command": true, "nkro": true, "rgblight": false, "backlight": false, "midi": false, "audio": false, "unicode": true, "bluetooth": false, "sleep_led": false, "oled_driver": true, "encoder": true, "bootmagic_lite": true}, "features": {"mousekey": true, "extrakey": true, "console": false, "command": true, "nkro": true, "rgblight": false, "backlight": false, "midi": false, "audio": false, "unicode": true, "bluetooth": false, "sleep_led": false, "oled_driver": true, "encoder": true, "bootmagic_lite": true}}}}