{"last_updated": "2021-01-30 21:16:28 GMT", "keyboards": {"gowla": {"keyboard_name": "Gowla Macro Pad", "keyboard_folder": "gowla", "keymaps": {}, "layouts": {"LAYOUT_ortho_3x3": {"key_count": 9, "layout": [{"x": 0, "y": 0}, {"x": 1, "y": 0}, {"x": 2, "y": 0}, {"x": 0, "y": 1}, {"x": 1, "y": 1}, {"x": 2, "y": 1}, {"x": 0, "y": 2}, {"x": 1, "y": 2}, {"x": 2, "y": 2}], "filename": "keyboards/gowla/gowla.h", "c_macro": false}}, "parse_errors": [], "parse_warnings": [], "maintainer": "Gowla", "url": "https://github.com/SamGowland/Gowla-Macro-Board", "width": 3, "height": 3, "diode_direction": "ROW2COL", "indicators": {}, "matrix_size": {"cols": 3, "rows": 3}, "matrix_pins": {"cols": ["B5", "B4", "E6"], "rows": ["D1", "D0", "D4"]}, "usb": {"vid": "0xFEED", "pid": "0xE9B6", "device_ver": "0x0001"}, "rgblight": {"sleep": false, "split": false}, "processor_type": "avr", "bootloader": "caterina", "platform": "unknown", "protocol": "LUFA", "processor": "atmega32u4", "community_layouts": [], "config_h_features": {"bootmagic": false, "mousekey": false, "extrakey": true, "console": false, "command": false, "sleep_led": false, "nkro": true, "backlight": false, "rgblight": false, "midi": false, "bluetooth": false, "audio": false, "fauxclicky": false}, "features": {"bootmagic": false, "mousekey": false, "extrakey": true, "console": false, "command": false, "sleep_led": false, "nkro": true, "backlight": false, "rgblight": false, "midi": false, "bluetooth": false, "audio": false, "fauxclicky": false}}}}