{"last_updated": "2021-01-10 04:19:57 GMT", "keyboards": {"40percentclub/6lit": {"keyboard_name": "6lit", "keyboard_folder": "40percentclub/6lit", "keymaps": {}, "layouts": {"LAYOUT_ortho_2x6": {"key_count": 12, "layout": [{"x": 0, "y": 0}, {"x": 1, "y": 0}, {"x": 2, "y": 0}, {"x": 3, "y": 0}, {"x": 4, "y": 0}, {"x": 5, "y": 0}, {"x": 0, "y": 1}, {"x": 1, "y": 1}, {"x": 2, "y": 1}, {"x": 3, "y": 1}, {"x": 4, "y": 1}, {"x": 5, "y": 1}], "filename": "keyboards/40percentclub/6lit/6lit.h", "c_macro": false}, "LAYOUT_ortho_2x3": {"key_count": 6, "layout": [{"x": 0, "y": 0}, {"x": 1, "y": 0}, {"x": 2, "y": 0}, {"x": 0, "y": 1}, {"x": 1, "y": 1}, {"x": 2, "y": 1}], "filename": "keyboards/40percentclub/6lit/6lit.h", "c_macro": false}, "LAYOUT_macro": {"key_count": 6, "layout": [{"x": 0, "y": 0}, {"x": 1, "y": 0}, {"x": 2, "y": 0}, {"x": 0, "y": 1}, {"x": 1, "y": 1}, {"x": 2, "y": 1}], "filename": "keyboards/40percentclub/6lit/6lit.h", "c_macro": false}, "LAYOUT_split": {"key_count": 12, "layout": [{"x": 0, "y": 0}, {"x": 1, "y": 0}, {"x": 2, "y": 0}, {"x": 3, "y": 0}, {"x": 4, "y": 0}, {"x": 5, "y": 0}, {"x": 0, "y": 1}, {"x": 1, "y": 1}, {"x": 2, "y": 1}, {"x": 3, "y": 1}, {"x": 4, "y": 1}, {"x": 5, "y": 1}], "filename": "keyboards/40percentclub/6lit/6lit.h", "c_macro": false}}, "parse_errors": [], "parse_warnings": [], "maintainer": "qmk", "url": "", "width": 6, "height": 2, "debounce": 5, "diode_direction": "COL2ROW", "indicators": {}, "matrix_size": {"cols": 3, "rows": 4}, "matrix_pins": {"cols": ["F6", "F7", "B1"], "rows": ["D7", "E6"]}, "usb": {"vid": "0xFEED", "pid": "0x0A0C", "device_ver": "0x0F61"}, "rgblight": {"sleep": false, "split": false}, "processor_type": "avr", "bootloader": "caterina", "platform": "unknown", "protocol": "LUFA", "processor": "atmega32u4", "community_layouts": [], "config_h_features": {"mousekey": true, "extrakey": true, "console": false, "command": true, "sleep_led": false, "nkro": true, "backlight": false, "rgblight": false, "midi": false, "unicode": false, "bluetooth": false, "audio": false, "fauxclicky": false, "bootmagic_lite": true}, "features": {"mousekey": true, "extrakey": true, "console": false, "command": true, "sleep_led": false, "nkro": true, "backlight": false, "rgblight": false, "midi": false, "unicode": false, "bluetooth": false, "audio": false, "fauxclicky": false, "bootmagic_lite": true}}}}