{"last_updated": "2021-01-21 06:02:10 GMT", "keyboards": {"ortho5by12": {"keyboard_name": "ortho5by12", "keyboard_folder": "ortho5by12", "keymaps": {}, "layouts": {"LAYOUT_ortho_5x12": {"key_count": 60, "layout": [{"w": 1, "x": 0, "y": 0}, {"w": 1, "x": 1, "y": 0}, {"w": 1, "x": 2, "y": 0}, {"w": 1, "x": 3, "y": 0}, {"w": 1, "x": 4, "y": 0}, {"w": 1, "x": 5, "y": 0}, {"w": 1, "x": 6, "y": 0}, {"w": 1, "x": 7, "y": 0}, {"w": 1, "x": 8, "y": 0}, {"w": 1, "x": 9, "y": 0}, {"w": 1, "x": 10, "y": 0}, {"w": 1, "x": 11, "y": 0}, {"w": 1, "x": 0, "y": 1}, {"w": 1, "x": 1, "y": 1}, {"w": 1, "x": 2, "y": 1}, {"w": 1, "x": 3, "y": 1}, {"w": 1, "x": 4, "y": 1}, {"w": 1, "x": 5, "y": 1}, {"w": 1, "x": 6, "y": 1}, {"w": 1, "x": 7, "y": 1}, {"w": 1, "x": 8, "y": 1}, {"w": 1, "x": 9, "y": 1}, {"w": 1, "x": 10, "y": 1}, {"w": 1, "x": 11, "y": 1}, {"w": 1, "x": 0, "y": 2}, {"w": 1, "x": 1, "y": 2}, {"w": 1, "x": 2, "y": 2}, {"w": 1, "x": 3, "y": 2}, {"w": 1, "x": 4, "y": 2}, {"w": 1, "x": 5, "y": 2}, {"w": 1, "x": 6, "y": 2}, {"w": 1, "x": 7, "y": 2}, {"w": 1, "x": 8, "y": 2}, {"w": 1, "x": 9, "y": 2}, {"w": 1, "x": 10, "y": 2}, {"w": 1, "x": 11, "y": 2}, {"w": 1, "x": 0, "y": 3}, {"w": 1, "x": 1, "y": 3}, {"w": 1, "x": 2, "y": 3}, {"w": 1, "x": 3, "y": 3}, {"w": 1, "x": 4, "y": 3}, {"w": 1, "x": 5, "y": 3}, {"w": 1, "x": 6, "y": 3}, {"w": 1, "x": 7, "y": 3}, {"w": 1, "x": 8, "y": 3}, {"w": 1, "x": 9, "y": 3}, {"w": 1, "x": 10, "y": 3}, {"w": 1, "x": 11, "y": 3}, {"w": 1, "x": 0, "y": 4}, {"w": 1, "x": 1, "y": 4}, {"w": 1, "x": 2, "y": 4}, {"w": 1, "x": 3, "y": 4}, {"w": 1, "x": 4, "y": 4}, {"w": 1, "x": 5, "y": 4}, {"w": 1, "x": 6, "y": 4}, {"w": 1, "x": 7, "y": 4}, {"w": 1, "x": 8, "y": 4}, {"w": 1, "x": 9, "y": 4}, {"w": 1, "x": 10, "y": 4}, {"w": 1, "x": 11, "y": 4}], "filename": "keyboards/ortho5by12/ortho5by12.h", "c_macro": false}, "LAYOUT_ortho_5x12_1x2uC": {"key_count": 59, "layout": [{"w": 1, "x": 0, "y": 0}, {"w": 1, "x": 1, "y": 0}, {"w": 1, "x": 2, "y": 0}, {"w": 1, "x": 3, "y": 0}, {"w": 1, "x": 4, "y": 0}, {"w": 1, "x": 5, "y": 0}, {"w": 1, "x": 6, "y": 0}, {"w": 1, "x": 7, "y": 0}, {"w": 1, "x": 8, "y": 0}, {"w": 1, "x": 9, "y": 0}, {"w": 1, "x": 10, "y": 0}, {"w": 1, "x": 11, "y": 0}, {"w": 1, "x": 0, "y": 1}, {"w": 1, "x": 1, "y": 1}, {"w": 1, "x": 2, "y": 1}, {"w": 1, "x": 3, "y": 1}, {"w": 1, "x": 4, "y": 1}, {"w": 1, "x": 5, "y": 1}, {"w": 1, "x": 6, "y": 1}, {"w": 1, "x": 7, "y": 1}, {"w": 1, "x": 8, "y": 1}, {"w": 1, "x": 9, "y": 1}, {"w": 1, "x": 10, "y": 1}, {"w": 1, "x": 11, "y": 1}, {"w": 1, "x": 0, "y": 2}, {"w": 1, "x": 1, "y": 2}, {"w": 1, "x": 2, "y": 2}, {"w": 1, "x": 3, "y": 2}, {"w": 1, "x": 4, "y": 2}, {"w": 1, "x": 5, "y": 2}, {"w": 1, "x": 6, "y": 2}, {"w": 1, "x": 7, "y": 2}, {"w": 1, "x": 8, "y": 2}, {"w": 1, "x": 9, "y": 2}, {"w": 1, "x": 10, "y": 2}, {"w": 1, "x": 11, "y": 2}, {"w": 1, "x": 0, "y": 3}, {"w": 1, "x": 1, "y": 3}, {"w": 1, "x": 2, "y": 3}, {"w": 1, "x": 3, "y": 3}, {"w": 1, "x": 4, "y": 3}, {"w": 1, "x": 5, "y": 3}, {"w": 1, "x": 6, "y": 3}, {"w": 1, "x": 7, "y": 3}, {"w": 1, "x": 8, "y": 3}, {"w": 1, "x": 9, "y": 3}, {"w": 1, "x": 10, "y": 3}, {"w": 1, "x": 11, "y": 3}, {"w": 1, "x": 0, "y": 4}, {"w": 1, "x": 1, "y": 4}, {"w": 1, "x": 2, "y": 4}, {"w": 1, "x": 3, "y": 4}, {"w": 1, "x": 4, "y": 4}, {"w": 2, "x": 5, "y": 4}, {"w": 1, "x": 7, "y": 4}, {"w": 1, "x": 8, "y": 4}, {"w": 1, "x": 9, "y": 4}, {"w": 1, "x": 10, "y": 4}, {"w": 1, "x": 11, "y": 4}], "filename": "keyboards/ortho5by12/ortho5by12.h", "c_macro": false}}, "parse_errors": [], "parse_warnings": [], "maintainer": "itsnoteasy", "url": "https://github.com/itsnoteasy/misc/blob/master/ortho5by12.zip", "width": 12, "height": 5, "debounce": 5, "diode_direction": "ROW2COL", "indicators": {}, "matrix_size": {"cols": 6, "rows": 10}, "matrix_pins": {"cols": ["C2", "D0", "D1", "D4", "C3", "C1"], "rows": ["B5", "B1", "B2", "B3", "B4", "C0", "D5", "D6", "D7", "B0"]}, "usb": {"vid": "0x16C0", "pid": "0x27DB", "device_ver": "0x0002"}, "rgblight": {"sleep": false, "split": false}, "processor_type": "avr", "bootloader": "USBasp", "platform": "unknown", "protocol": "V-USB", "processor": "atmega328p", "community_layouts": [], "config_h_features": {"mousekey": false, "extrakey": true, "console": false, "command": false, "sleep_led": false, "nkro": false, "backlight": false, "rgblight": false, "midi": false, "unicode": false, "bluetooth": false, "audio": false, "fauxclicky": false, "bootmagic_lite": true}, "features": {"mousekey": false, "extrakey": true, "console": false, "command": false, "sleep_led": false, "nkro": false, "backlight": false, "rgblight": false, "midi": false, "unicode": false, "bluetooth": false, "audio": false, "fauxclicky": false, "bootmagic_lite": true}}}}